numpy_html/__init__.py
numpy_html/formatter.py
numpy_html/renderer.py
numpy_html-1.0.0.dist-info/LICENSE.md
numpy_html-1.0.0.dist-info/WHEEL
numpy_html-1.0.0.dist-info/METADATA
numpy_html-1.0.0.dist-info/RECORD
