Metadata-Version: 2.1
Name: numpy-html
Version: 1.0.0
Summary: A simple table renderer for numpy arrays. Provides a rich display hook for use with Jupyter Lab / Notebook.
License: MIT
Author: Angus Hollands
Author-email: goosey15@gmail.com
Requires-Python: >=3.6
Classifier: Development Status :: 3 - Alpha
Classifier: Framework :: Jupyter
Classifier: License :: OSI Approved :: MIT License
Classifier: Operating System :: OS Independent
Classifier: Programming Language :: Python :: 3
Classifier: Programming Language :: Python :: 3.10
Classifier: Programming Language :: Python :: 3.6
Classifier: Programming Language :: Python :: 3.7
Classifier: Programming Language :: Python :: 3.8
Classifier: Programming Language :: Python :: 3.9
Requires-Dist: numpy
